siq/__init__.py
siq/get_data.py
siq-0.4.1.dist-info/METADATA
siq-0.4.1.dist-info/WHEEL
siq-0.4.1.dist-info/top_level.txt
siq-0.4.1.dist-info/RECORD
