Metadata-Version: 2.4
Name: siq
Version: 0.4.1
Summary: deep perceptual resampling and super resolution with antspyx
Author-email: "Avants, Gosselin, Tustison, Reardon" <stnava@gmail.com>
License: Apache-2.0
Project-URL: Homepage, https://github.com/stnava/siq
Keywords: super-resolution,deep learning,ants,resampling,neuroimaging
Classifier: Programming Language :: Python :: 3
Classifier: License :: OSI Approved :: Apache Software License
Classifier: Operating System :: OS Independent
Requires-Python: >=3.7
